ffrec/__init__.py
ffrec/_version.py
ffrec/main.py
ffrec/lib/parse_args.py
ffrec/lib/record_screen.py
ffrec-0.4.0.dist-info/licenses/LICENSE-CC.txt
ffrec-0.4.0.dist-info/licenses/LICENSE-apache.txt
ffrec-0.4.0.dist-info/METADATA
ffrec-0.4.0.dist-info/WHEEL
ffrec-0.4.0.dist-info/entry_points.txt
ffrec-0.4.0.dist-info/top_level.txt
ffrec-0.4.0.dist-info/RECORD
