Metadata-Version: 2.4
Name: ffrec
Version: 0.4.0
Summary: Records the screen, using Python
Author-email: Jeff Moe <moe@spacecruft.org>
License: Apache 2.0
Project-URL: Homepage, https://spacecruft.org/deepcrayon/ffrec
Project-URL: Documentation, https://spacecruft.org/deepcrayon/ffrec
Project-URL: Repository, https://spacecruft.org/deepcrayon/ffrec
Project-URL: Issues, https://spacecruft.org/deepcrayon/ffrec
Project-URL: Changelog, https://spacecruft.org/deepcrayon/ffrec/raw/branch/main/CHANGELOG.txt
Keywords: ffmpeg,record,screencap
Classifier: Development Status :: 3 - Alpha
Classifier: Environment :: Console
Classifier: Environment :: GPU
Classifier: Intended Audience :: Developers
Classifier: Intended Audience :: End Users/Desktop
Classifier: License :: OSI Approved :: Apache Software License
Classifier: Natural Language :: English
Classifier: Operating System :: OS Independent
Classifier: Programming Language :: Python :: 3
Classifier: Topic :: Multimedia :: Graphics :: Capture :: Screen Capture
Classifier: Topic :: Multimedia :: Sound/Audio
Classifier: Topic :: Multimedia :: Video :: Capture
Requires-Python: >=3.9
License-File: LICENSE-CC.txt
License-File: LICENSE-apache.txt
Requires-Dist: asyncio
Requires-Dist: python-ffmpeg
Provides-Extra: dev
Requires-Dist: black; extra == "dev"
Requires-Dist: ruff; extra == "dev"
Requires-Dist: setuptools-scm; extra == "dev"
Requires-Dist: twine; extra == "dev"
Dynamic: license-file
